{
  "unversionedId": "v1/BlockID Admin Console/Admin Guide/Authentication Configuration/Z73440ef0-77e6-4977-8eab-98c41255b244",
  "id": "v1/BlockID Admin Console/Admin Guide/Authentication Configuration/Z73440ef0-77e6-4977-8eab-98c41255b244",
  "isDocsHomePage": false,
  "title": "Authentication Scheme",
  "description": "Authentication schemes are a series of building blocks for authentication. Each block represents a different mechanism for authenticating and enables multi-factor authentication (MFA).",
  "source": "@site/docs/v1/BlockID Admin Console/Admin Guide/Authentication Configuration/3_authentication-.md.mdx",
  "sourceDirName": "v1/BlockID Admin Console/Admin Guide/Authentication Configuration",
  "slug": "/v1/authentication-scheme",
  "permalink": "/docs/v1/authentication-scheme",
  "tags": [],
  "version": "current",
  "sidebarPosition": 3,
  "frontMatter": {
    "slug": "/v1/authentication-scheme",
    "id": "Z73440ef0-77e6-4977-8eab-98c41255b244"
  },
  "sidebar": "mySidebar",
  "previous": {
    "title": "Authentication Modules",
    "permalink": "/docs/v1/authentication-modules"
  },
  "next": {
    "title": "Software and Hardware OTP Support",
    "permalink": "/docs/v1/software-and-hardware-otp-support"
  }
}