{
  "unversionedId": "v1/BlockID Credential Provider/internal-guide-",
  "id": "v1/BlockID Credential Provider/internal-guide-",
  "isDocsHomePage": false,
  "title": "internal-guide-",
  "description": "Metadata_Start",
  "source": "@site/docs/v1/BlockID Credential Provider/4_internal-guide-.md",
  "sourceDirName": "v1/BlockID Credential Provider",
  "slug": "/v1/BlockID Credential Provider/internal-guide-",
  "permalink": "/docs/v1/BlockID Credential Provider/internal-guide-",
  "tags": [],
  "version": "current",
  "sidebarPosition": 4,
  "frontMatter": {},
  "sidebar": "mySidebar",
  "previous": {
    "title": "Core Concepts of BlockID Credential Provider Guide",
    "permalink": "/docs/v1/core-concepts-of-blockid-credential-provider-guide"
  },
  "next": {
    "title": "Internal Guide - BlockID Credential Provider",
    "permalink": "/docs/v1/internal-guide-blockid-credential-provider"
  }
}