{
  "permalink": "/blog/2021/08/08/intro",
  "editUrl": "https://github.com/1KBlockID/devx_frontend/tree/develop/blog/blog/2021-08-08-intro.md",
  "source": "@site/blog/2021-08-08-intro.md",
  "title": "Tutorial Intro",
  "description": "Let's discover Docusaurus in less than 5 minutes.",
  "date": "2021-08-08T00:00:00.000Z",
  "formattedDate": "August 8, 2021",
  "tags": [],
  "readingTime": 0.395,
  "truncated": false,
  "authors": [],
  "prevItem": {
    "title": "Welcome",
    "permalink": "/blog/welcome"
  },
  "nextItem": {
    "title": "MDX Blog Post",
    "permalink": "/blog/mdx-blog-post"
  }
}